[
    {
        "url": "https://api.github.com/repos/dracula/dracula-theme/issues/comments/155204731",
        "html_url": "https://github.com/dracula/dracula-theme/issues/116#issuecomment-155204731",
        "issue_url": "https://api.github.com/repos/dracula/dracula-theme/issues/116",
        "id": 155204731,
        "node_id": "MDEyOklzc3VlQ29tbWVudDE1NTIwNDczMQ==",
        "user": {
            "login": "zenorocha",
            "id": 398893,
            "node_id": "MDQ6VXNlcjM5ODg5Mw==",
            "avatar_url": "https://avatars.githubusercontent.com/u/398893?v=4",
            "gravatar_id": "",
            "url": "https://api.github.com/users/zenorocha",
            "html_url": "https://github.com/zenorocha",
            "followers_url": "https://api.github.com/users/zenorocha/followers",
            "following_url": "https://api.github.com/users/zenorocha/following{/other_user}",
            "gists_url": "https://api.github.com/users/zenorocha/gists{/gist_id}",
            "starred_url": "https://api.github.com/users/zenorocha/starred{/owner}{/repo}",
            "subscriptions_url": "https://api.github.com/users/zenorocha/subscriptions",
            "organizations_url": "https://api.github.com/users/zenorocha/orgs",
            "repos_url": "https://api.github.com/users/zenorocha/repos",
            "events_url": "https://api.github.com/users/zenorocha/events{/privacy}",
            "received_events_url": "https://api.github.com/users/zenorocha/received_events",
            "type": "User",
            "user_view_type": "public",
            "site_admin": false
        },
        "created_at": "2015-11-09T21:36:54Z",
        "updated_at": "2015-11-09T21:36:54Z",
        "body": "@film42 @avelino any ideas?\n",
        "author_association": "CONTRIBUTOR",
        "reactions": {
            "url": "https://api.github.com/repos/dracula/dracula-theme/issues/comments/155204731/reactions",
            "total_count": 0,
            "+1": 0,
            "-1": 0,
            "laugh": 0,
            "hooray": 0,
            "confused": 0,
            "heart": 0,
            "rocket": 0,
            "eyes": 0
        },
        "performed_via_github_app": null
    },
    {
        "url": "https://api.github.com/repos/dracula/dracula-theme/issues/comments/155261963",
        "html_url": "https://github.com/dracula/dracula-theme/issues/116#issuecomment-155261963",
        "issue_url": "https://api.github.com/repos/dracula/dracula-theme/issues/116",
        "id": 155261963,
        "node_id": "MDEyOklzc3VlQ29tbWVudDE1NTI2MTk2Mw==",
        "user": {
            "login": "film42",
            "id": 1043908,
            "node_id": "MDQ6VXNlcjEwNDM5MDg=",
            "avatar_url": "https://avatars.githubusercontent.com/u/1043908?v=4",
            "gravatar_id": "",
            "url": "https://api.github.com/users/film42",
            "html_url": "https://github.com/film42",
            "followers_url": "https://api.github.com/users/film42/followers",
            "following_url": "https://api.github.com/users/film42/following{/other_user}",
            "gists_url": "https://api.github.com/users/film42/gists{/gist_id}",
            "starred_url": "https://api.github.com/users/film42/starred{/owner}{/repo}",
            "subscriptions_url": "https://api.github.com/users/film42/subscriptions",
            "organizations_url": "https://api.github.com/users/film42/orgs",
            "repos_url": "https://api.github.com/users/film42/repos",
            "events_url": "https://api.github.com/users/film42/events{/privacy}",
            "received_events_url": "https://api.github.com/users/film42/received_events",
            "type": "User",
            "user_view_type": "public",
            "site_admin": false
        },
        "created_at": "2015-11-10T02:20:20Z",
        "updated_at": "2015-11-10T02:20:20Z",
        "body": "This problem was mentioned in the [Emacs Love PR](https://github.com/zenorocha/dracula-theme/pull/98#issuecomment-152603771). There's not a ton we can do about terminal emacs until emacs supports True Color (24bit RGB) values.\n\nLooks like someone put a patch together (though the thread is quite old): http://emacs.1067599.n5.nabble.com/RFC-Add-tty-True-Color-support-td299962.html\n",
        "author_association": "CONTRIBUTOR",
        "reactions": {
            "url": "https://api.github.com/repos/dracula/dracula-theme/issues/comments/155261963/reactions",
            "total_count": 0,
            "+1": 0,
            "-1": 0,
            "laugh": 0,
            "hooray": 0,
            "confused": 0,
            "heart": 0,
            "rocket": 0,
            "eyes": 0
        },
        "performed_via_github_app": null
    },
    {
        "url": "https://api.github.com/repos/dracula/dracula-theme/issues/comments/155295527",
        "html_url": "https://github.com/dracula/dracula-theme/issues/116#issuecomment-155295527",
        "issue_url": "https://api.github.com/repos/dracula/dracula-theme/issues/116",
        "id": 155295527,
        "node_id": "MDEyOklzc3VlQ29tbWVudDE1NTI5NTUyNw==",
        "user": {
            "login": "jonathanchu",
            "id": 66164,
            "node_id": "MDQ6VXNlcjY2MTY0",
            "avatar_url": "https://avatars.githubusercontent.com/u/66164?v=4",
            "gravatar_id": "",
            "url": "https://api.github.com/users/jonathanchu",
            "html_url": "https://github.com/jonathanchu",
            "followers_url": "https://api.github.com/users/jonathanchu/followers",
            "following_url": "https://api.github.com/users/jonathanchu/following{/other_user}",
            "gists_url": "https://api.github.com/users/jonathanchu/gists{/gist_id}",
            "starred_url": "https://api.github.com/users/jonathanchu/starred{/owner}{/repo}",
            "subscriptions_url": "https://api.github.com/users/jonathanchu/subscriptions",
            "organizations_url": "https://api.github.com/users/jonathanchu/orgs",
            "repos_url": "https://api.github.com/users/jonathanchu/repos",
            "events_url": "https://api.github.com/users/jonathanchu/events{/privacy}",
            "received_events_url": "https://api.github.com/users/jonathanchu/received_events",
            "type": "User",
            "user_view_type": "public",
            "site_admin": false
        },
        "created_at": "2015-11-10T05:22:33Z",
        "updated_at": "2015-11-10T05:22:33Z",
        "body": "@film42 thanks for response and explanation - I appreciate the input! :)\n\nFor this emacs theme, do you think there could be a work-around similar to what emacs solarized proposes?  https://github.com/sellout/emacs-color-theme-solarized#important-note-for-terminal-users\n\nI'm not really sure what to do there or if that would be a viable solution for this.\n\nThanks!\n",
        "author_association": "NONE",
        "reactions": {
            "url": "https://api.github.com/repos/dracula/dracula-theme/issues/comments/155295527/reactions",
            "total_count": 0,
            "+1": 0,
            "-1": 0,
            "laugh": 0,
            "hooray": 0,
            "confused": 0,
            "heart": 0,
            "rocket": 0,
            "eyes": 0
        },
        "performed_via_github_app": null
    },
    {
        "url": "https://api.github.com/repos/dracula/dracula-theme/issues/comments/162354408",
        "html_url": "https://github.com/dracula/dracula-theme/issues/116#issuecomment-162354408",
        "issue_url": "https://api.github.com/repos/dracula/dracula-theme/issues/116",
        "id": 162354408,
        "node_id": "MDEyOklzc3VlQ29tbWVudDE2MjM1NDQwOA==",
        "user": {
            "login": "121onto",
            "id": 13111271,
            "node_id": "MDQ6VXNlcjEzMTExMjcx",
            "avatar_url": "https://avatars.githubusercontent.com/u/13111271?v=4",
            "gravatar_id": "",
            "url": "https://api.github.com/users/121onto",
            "html_url": "https://github.com/121onto",
            "followers_url": "https://api.github.com/users/121onto/followers",
            "following_url": "https://api.github.com/users/121onto/following{/other_user}",
            "gists_url": "https://api.github.com/users/121onto/gists{/gist_id}",
            "starred_url": "https://api.github.com/users/121onto/starred{/owner}{/repo}",
            "subscriptions_url": "https://api.github.com/users/121onto/subscriptions",
            "organizations_url": "https://api.github.com/users/121onto/orgs",
            "repos_url": "https://api.github.com/users/121onto/repos",
            "events_url": "https://api.github.com/users/121onto/events{/privacy}",
            "received_events_url": "https://api.github.com/users/121onto/received_events",
            "type": "User",
            "user_view_type": "public",
            "site_admin": false
        },
        "created_at": "2015-12-06T22:28:49Z",
        "updated_at": "2015-12-06T23:53:22Z",
        "body": "@jonathanchu I got this theme to work by re-installing emacs with homebrew:\n\n``` bash\nbrew install --srgb --cocoa --HEAD\n```\n\n**Edit**: reinstalling emacs probably isn't what fixed the problem.  Try adding the following line to the end of your init.el:\n\n``` lisp\n(custom-set-faces (if (not window-system) '(default ((t (:background \"nil\"))))))\n```\n\nA small improvement, though colors are still inaccurate:\n\n![screen shot 2015-12-06 at 3 40 44 pm](https://cloud.githubusercontent.com/assets/13111271/11616432/d093960c-9c2f-11e5-8534-47f394b0f112.png)\n",
        "author_association": "NONE",
        "reactions": {
            "url": "https://api.github.com/repos/dracula/dracula-theme/issues/comments/162354408/reactions",
            "total_count": 0,
            "+1": 0,
            "-1": 0,
            "laugh": 0,
            "hooray": 0,
            "confused": 0,
            "heart": 0,
            "rocket": 0,
            "eyes": 0
        },
        "performed_via_github_app": null
    },
    {
        "url": "https://api.github.com/repos/dracula/dracula-theme/issues/comments/162397574",
        "html_url": "https://github.com/dracula/dracula-theme/issues/116#issuecomment-162397574",
        "issue_url": "https://api.github.com/repos/dracula/dracula-theme/issues/116",
        "id": 162397574,
        "node_id": "MDEyOklzc3VlQ29tbWVudDE2MjM5NzU3NA==",
        "user": {
            "login": "121onto",
            "id": 13111271,
            "node_id": "MDQ6VXNlcjEzMTExMjcx",
            "avatar_url": "https://avatars.githubusercontent.com/u/13111271?v=4",
            "gravatar_id": "",
            "url": "https://api.github.com/users/121onto",
            "html_url": "https://github.com/121onto",
            "followers_url": "https://api.github.com/users/121onto/followers",
            "following_url": "https://api.github.com/users/121onto/following{/other_user}",
            "gists_url": "https://api.github.com/users/121onto/gists{/gist_id}",
            "starred_url": "https://api.github.com/users/121onto/starred{/owner}{/repo}",
            "subscriptions_url": "https://api.github.com/users/121onto/subscriptions",
            "organizations_url": "https://api.github.com/users/121onto/orgs",
            "repos_url": "https://api.github.com/users/121onto/repos",
            "events_url": "https://api.github.com/users/121onto/events{/privacy}",
            "received_events_url": "https://api.github.com/users/121onto/received_events",
            "type": "User",
            "user_view_type": "public",
            "site_admin": false
        },
        "created_at": "2015-12-07T03:07:05Z",
        "updated_at": "2015-12-07T03:16:26Z",
        "body": "Update:\n\nI have this working now.  Here is what I did.\n1. Uninstall emacs and download source:\n   \n   ``` bash\n   brew uninstall emacs\n   brew unlink emacs\n   cd ~/temp\n   git clone https://github.com/emacs-mirror/emacs.git\n   cd emacs\n   ```\n2. Install true color patch available [here](https://gist.github.com/choppsv1/73d51cedd3e8ec72e1c1)\n   \n   ``` bash\n   git reset --hard \"emacs-24.3\"\n   curl -O https://gist.githubusercontent.com/choppsv1/73d51cedd3e8ec72e1c1/raw/e54ef720cb55ac539adefde9bc87a14ea05b0b99/emacs-24.3-24bit.diff\n   patch -p1 < emacs-24.3-24bit.diff\n   ```\n3. Install emacs from source:\n   \n   ``` bash\n   ./autogen.sh\n   ./configure \\\n   --prefix=/usr/local/Cellar/emacs-24-with-24bit-colors/1.0 \\\n   --enable-locallisppath=/usr/local/share/emacs/site-lisp \\\n   --infodir=/usr/local/Cellar/emacs-24-with-24bit-colors/1.0/share/info/emacs \\\n   --with-xml2 \\\n   --without-dbus \\\n   --without-gnutls \\\n   --with-ns \\\n   --disable-ns-self-contained\n   make\n   make install\n   cp -R nextstep/Emacs.app /usr/local/Cellar/emacs-24-with-24bit-colors/1.0/\n   chmod 0555 /usr/local/Cellar/emacs-24-with-24bit-colors/1.0/Emacs.app\n   printf '#!/bin/bash\\nexec /usr/local/Cellar/emacs-24-with-24bit-colors/1.0/Emacs.app/Contents/MacOS/Emacs \"$@\"' >> /usr/local/Cellar/emacs-24-with-24bit-colors/1.0/bin/emacs\n   chmod 0555 /usr/local/Cellar/emacs-24-with-24bit-colors/1.0/bin/emacs\n   ln -s /usr/local/Cellar/emacs-24-with-24bit-colors/1.0/bin/emacs /usr/local/bin/emacs\n   ```\n\nOne issue, the patch is written for Emacs 24.3, it does not seem to work with more recent versions.\n\n![screen shot 2015-12-06 at 7 15 43 pm](https://cloud.githubusercontent.com/assets/13111271/11618301/cc3925ae-9c4d-11e5-927d-ab6e452148d7.png)\n",
        "author_association": "NONE",
        "reactions": {
            "url": "https://api.github.com/repos/dracula/dracula-theme/issues/comments/162397574/reactions",
            "total_count": 0,
            "+1": 0,
            "-1": 0,
            "laugh": 0,
            "hooray": 0,
            "confused": 0,
            "heart": 0,
            "rocket": 0,
            "eyes": 0
        },
        "performed_via_github_app": null
    },
    {
        "url": "https://api.github.com/repos/dracula/dracula-theme/issues/comments/162602885",
        "html_url": "https://github.com/dracula/dracula-theme/issues/116#issuecomment-162602885",
        "issue_url": "https://api.github.com/repos/dracula/dracula-theme/issues/116",
        "id": 162602885,
        "node_id": "MDEyOklzc3VlQ29tbWVudDE2MjYwMjg4NQ==",
        "user": {
            "login": "film42",
            "id": 1043908,
            "node_id": "MDQ6VXNlcjEwNDM5MDg=",
            "avatar_url": "https://avatars.githubusercontent.com/u/1043908?v=4",
            "gravatar_id": "",
            "url": "https://api.github.com/users/film42",
            "html_url": "https://github.com/film42",
            "followers_url": "https://api.github.com/users/film42/followers",
            "following_url": "https://api.github.com/users/film42/following{/other_user}",
            "gists_url": "https://api.github.com/users/film42/gists{/gist_id}",
            "starred_url": "https://api.github.com/users/film42/starred{/owner}{/repo}",
            "subscriptions_url": "https://api.github.com/users/film42/subscriptions",
            "organizations_url": "https://api.github.com/users/film42/orgs",
            "repos_url": "https://api.github.com/users/film42/repos",
            "events_url": "https://api.github.com/users/film42/events{/privacy}",
            "received_events_url": "https://api.github.com/users/film42/received_events",
            "type": "User",
            "user_view_type": "public",
            "site_admin": false
        },
        "created_at": "2015-12-07T17:38:27Z",
        "updated_at": "2015-12-07T17:38:27Z",
        "body": "Interesting. I'll try compiling the patch in later tonight to see what I can come up with. This isn't really related to this project, because it would be strange to ask users to patch their emacs for a theme, but it sure is interesting :)\n",
        "author_association": "CONTRIBUTOR",
        "reactions": {
            "url": "https://api.github.com/repos/dracula/dracula-theme/issues/comments/162602885/reactions",
            "total_count": 0,
            "+1": 0,
            "-1": 0,
            "laugh": 0,
            "hooray": 0,
            "confused": 0,
            "heart": 0,
            "rocket": 0,
            "eyes": 0
        },
        "performed_via_github_app": null
    },
    {
        "url": "https://api.github.com/repos/dracula/dracula-theme/issues/comments/162772652",
        "html_url": "https://github.com/dracula/dracula-theme/issues/116#issuecomment-162772652",
        "issue_url": "https://api.github.com/repos/dracula/dracula-theme/issues/116",
        "id": 162772652,
        "node_id": "MDEyOklzc3VlQ29tbWVudDE2Mjc3MjY1Mg==",
        "user": {
            "login": "jonathanchu",
            "id": 66164,
            "node_id": "MDQ6VXNlcjY2MTY0",
            "avatar_url": "https://avatars.githubusercontent.com/u/66164?v=4",
            "gravatar_id": "",
            "url": "https://api.github.com/users/jonathanchu",
            "html_url": "https://github.com/jonathanchu",
            "followers_url": "https://api.github.com/users/jonathanchu/followers",
            "following_url": "https://api.github.com/users/jonathanchu/following{/other_user}",
            "gists_url": "https://api.github.com/users/jonathanchu/gists{/gist_id}",
            "starred_url": "https://api.github.com/users/jonathanchu/starred{/owner}{/repo}",
            "subscriptions_url": "https://api.github.com/users/jonathanchu/subscriptions",
            "organizations_url": "https://api.github.com/users/jonathanchu/orgs",
            "repos_url": "https://api.github.com/users/jonathanchu/repos",
            "events_url": "https://api.github.com/users/jonathanchu/events{/privacy}",
            "received_events_url": "https://api.github.com/users/jonathanchu/received_events",
            "type": "User",
            "user_view_type": "public",
            "site_admin": false
        },
        "created_at": "2015-12-08T05:36:32Z",
        "updated_at": "2015-12-08T05:36:32Z",
        "body": "@121onto cheers, thanks for the detailed writeup!  I'll give this a try too and see how it goes.  :smile: :+1: \n",
        "author_association": "NONE",
        "reactions": {
            "url": "https://api.github.com/repos/dracula/dracula-theme/issues/comments/162772652/reactions",
            "total_count": 0,
            "+1": 0,
            "-1": 0,
            "laugh": 0,
            "hooray": 0,
            "confused": 0,
            "heart": 0,
            "rocket": 0,
            "eyes": 0
        },
        "performed_via_github_app": null
    },
    {
        "url": "https://api.github.com/repos/dracula/dracula-theme/issues/comments/162788131",
        "html_url": "https://github.com/dracula/dracula-theme/issues/116#issuecomment-162788131",
        "issue_url": "https://api.github.com/repos/dracula/dracula-theme/issues/116",
        "id": 162788131,
        "node_id": "MDEyOklzc3VlQ29tbWVudDE2Mjc4ODEzMQ==",
        "user": {
            "login": "film42",
            "id": 1043908,
            "node_id": "MDQ6VXNlcjEwNDM5MDg=",
            "avatar_url": "https://avatars.githubusercontent.com/u/1043908?v=4",
            "gravatar_id": "",
            "url": "https://api.github.com/users/film42",
            "html_url": "https://github.com/film42",
            "followers_url": "https://api.github.com/users/film42/followers",
            "following_url": "https://api.github.com/users/film42/following{/other_user}",
            "gists_url": "https://api.github.com/users/film42/gists{/gist_id}",
            "starred_url": "https://api.github.com/users/film42/starred{/owner}{/repo}",
            "subscriptions_url": "https://api.github.com/users/film42/subscriptions",
            "organizations_url": "https://api.github.com/users/film42/orgs",
            "repos_url": "https://api.github.com/users/film42/repos",
            "events_url": "https://api.github.com/users/film42/events{/privacy}",
            "received_events_url": "https://api.github.com/users/film42/received_events",
            "type": "User",
            "user_view_type": "public",
            "site_admin": false
        },
        "created_at": "2015-12-08T06:32:22Z",
        "updated_at": "2015-12-08T06:34:44Z",
        "body": "Looks like @choppsv1 also made a patch for emacs 24.5: https://gist.github.com/choppsv1/e8198df70cb1778b04d6\n\nI followed the sam configure flags as @121onto , only with the emacs 24.5 branch.\n\nI then set `export ITERM_24BIT=1` to enable it in my shell.\n\nAt first I was getting 24 bit color, but iTerm was failing to render the text (I could tell it was encoded 24bit, but nothing worked, no color at all), so I searched around and someone said that to get vim working with 24 bit colors and iTerm, you need to download the latest [nightly build](https://iterm2.com/nightly/latest). After that, things worked great :).\n\n![image](https://cloud.githubusercontent.com/assets/1043908/11649267/7c017fc6-9d3a-11e5-9f34-2cc13e058ad2.png)\n",
        "author_association": "CONTRIBUTOR",
        "reactions": {
            "url": "https://api.github.com/repos/dracula/dracula-theme/issues/comments/162788131/reactions",
            "total_count": 0,
            "+1": 0,
            "-1": 0,
            "laugh": 0,
            "hooray": 0,
            "confused": 0,
            "heart": 0,
            "rocket": 0,
            "eyes": 0
        },
        "performed_via_github_app": null
    },
    {
        "url": "https://api.github.com/repos/dracula/dracula-theme/issues/comments/162790527",
        "html_url": "https://github.com/dracula/dracula-theme/issues/116#issuecomment-162790527",
        "issue_url": "https://api.github.com/repos/dracula/dracula-theme/issues/116",
        "id": 162790527,
        "node_id": "MDEyOklzc3VlQ29tbWVudDE2Mjc5MDUyNw==",
        "user": {
            "login": "121onto",
            "id": 13111271,
            "node_id": "MDQ6VXNlcjEzMTExMjcx",
            "avatar_url": "https://avatars.githubusercontent.com/u/13111271?v=4",
            "gravatar_id": "",
            "url": "https://api.github.com/users/121onto",
            "html_url": "https://github.com/121onto",
            "followers_url": "https://api.github.com/users/121onto/followers",
            "following_url": "https://api.github.com/users/121onto/following{/other_user}",
            "gists_url": "https://api.github.com/users/121onto/gists{/gist_id}",
            "starred_url": "https://api.github.com/users/121onto/starred{/owner}{/repo}",
            "subscriptions_url": "https://api.github.com/users/121onto/subscriptions",
            "organizations_url": "https://api.github.com/users/121onto/orgs",
            "repos_url": "https://api.github.com/users/121onto/repos",
            "events_url": "https://api.github.com/users/121onto/events{/privacy}",
            "received_events_url": "https://api.github.com/users/121onto/received_events",
            "type": "User",
            "user_view_type": "public",
            "site_admin": false
        },
        "created_at": "2015-12-08T06:42:45Z",
        "updated_at": "2015-12-08T06:42:45Z",
        "body": "@film42 thank you!  \n\nSo much effort, and the second we upgrade it all goes away.  I am in touch with the emacs dev team and will point this out to them.  Would be great to get true color support in the next release.\n",
        "author_association": "NONE",
        "reactions": {
            "url": "https://api.github.com/repos/dracula/dracula-theme/issues/comments/162790527/reactions",
            "total_count": 0,
            "+1": 0,
            "-1": 0,
            "laugh": 0,
            "hooray": 0,
            "confused": 0,
            "heart": 0,
            "rocket": 0,
            "eyes": 0
        },
        "performed_via_github_app": null
    },
    {
        "url": "https://api.github.com/repos/dracula/dracula-theme/issues/comments/189999901",
        "html_url": "https://github.com/dracula/dracula-theme/issues/116#issuecomment-189999901",
        "issue_url": "https://api.github.com/repos/dracula/dracula-theme/issues/116",
        "id": 189999901,
        "node_id": "MDEyOklzc3VlQ29tbWVudDE4OTk5OTkwMQ==",
        "user": {
            "login": "cstrahan",
            "id": 143982,
            "node_id": "MDQ6VXNlcjE0Mzk4Mg==",
            "avatar_url": "https://avatars.githubusercontent.com/u/143982?v=4",
            "gravatar_id": "",
            "url": "https://api.github.com/users/cstrahan",
            "html_url": "https://github.com/cstrahan",
            "followers_url": "https://api.github.com/users/cstrahan/followers",
            "following_url": "https://api.github.com/users/cstrahan/following{/other_user}",
            "gists_url": "https://api.github.com/users/cstrahan/gists{/gist_id}",
            "starred_url": "https://api.github.com/users/cstrahan/starred{/owner}{/repo}",
            "subscriptions_url": "https://api.github.com/users/cstrahan/subscriptions",
            "organizations_url": "https://api.github.com/users/cstrahan/orgs",
            "repos_url": "https://api.github.com/users/cstrahan/repos",
            "events_url": "https://api.github.com/users/cstrahan/events{/privacy}",
            "received_events_url": "https://api.github.com/users/cstrahan/received_events",
            "type": "User",
            "user_view_type": "public",
            "site_admin": false
        },
        "created_at": "2016-02-29T02:15:34Z",
        "updated_at": "2016-02-29T02:15:34Z",
        "body": "@121onto Have you heard anything from the emacs developers? I've contacted @ruediger to see if he's still working on it. If 24-bit color support isn't currently underway, it's something that I'd be willing to take on and contribute upstream to emacs.\n",
        "author_association": "NONE",
        "reactions": {
            "url": "https://api.github.com/repos/dracula/dracula-theme/issues/comments/189999901/reactions",
            "total_count": 0,
            "+1": 0,
            "-1": 0,
            "laugh": 0,
            "hooray": 0,
            "confused": 0,
            "heart": 0,
            "rocket": 0,
            "eyes": 0
        },
        "performed_via_github_app": null
    },
    {
        "url": "https://api.github.com/repos/dracula/dracula-theme/issues/comments/190197898",
        "html_url": "https://github.com/dracula/dracula-theme/issues/116#issuecomment-190197898",
        "issue_url": "https://api.github.com/repos/dracula/dracula-theme/issues/116",
        "id": 190197898,
        "node_id": "MDEyOklzc3VlQ29tbWVudDE5MDE5Nzg5OA==",
        "user": {
            "login": "choppsv1",
            "id": 3074665,
            "node_id": "MDQ6VXNlcjMwNzQ2NjU=",
            "avatar_url": "https://avatars.githubusercontent.com/u/3074665?v=4",
            "gravatar_id": "",
            "url": "https://api.github.com/users/choppsv1",
            "html_url": "https://github.com/choppsv1",
            "followers_url": "https://api.github.com/users/choppsv1/followers",
            "following_url": "https://api.github.com/users/choppsv1/following{/other_user}",
            "gists_url": "https://api.github.com/users/choppsv1/gists{/gist_id}",
            "starred_url": "https://api.github.com/users/choppsv1/starred{/owner}{/repo}",
            "subscriptions_url": "https://api.github.com/users/choppsv1/subscriptions",
            "organizations_url": "https://api.github.com/users/choppsv1/orgs",
            "repos_url": "https://api.github.com/users/choppsv1/repos",
            "events_url": "https://api.github.com/users/choppsv1/events{/privacy}",
            "received_events_url": "https://api.github.com/users/choppsv1/received_events",
            "type": "User",
            "user_view_type": "public",
            "site_admin": false
        },
        "created_at": "2016-02-29T12:54:36Z",
        "updated_at": "2016-02-29T12:54:36Z",
        "body": "FWIW, I also have a homebrew tap setup that builds the patched emacs which is a lot easier than doing it by hand. :) The tap is choppsv1/term24/emacs.\n",
        "author_association": "NONE",
        "reactions": {
            "url": "https://api.github.com/repos/dracula/dracula-theme/issues/comments/190197898/reactions",
            "total_count": 1,
            "+1": 1,
            "-1": 0,
            "laugh": 0,
            "hooray": 0,
            "confused": 0,
            "heart": 0,
            "rocket": 0,
            "eyes": 0
        },
        "performed_via_github_app": null
    }
]